yaml_common/__init__.py
yaml_common/__main__.py
yaml_common/libcommon.py
yaml_common/libmerge.py
yaml_common/main.py
re_yaml_common-2.0.4.dist-info/LICENSE
re_yaml_common-2.0.4.dist-info/METADATA
re_yaml_common-2.0.4.dist-info/WHEEL
re_yaml_common-2.0.4.dist-info/entry_points.txt
re_yaml_common-2.0.4.dist-info/RECORD
