Metadata-Version: 2.1
Name: re-yaml-common
Version: 2.0.4
Summary: 
License: SSPL-1.0
Author: Philipp Gayret
Author-email: philipp@release-engineers.com
Requires-Python: >=3.11,<4.0
Classifier: License :: Other/Proprietary License
Classifier: Programming Language :: Python :: 3
Classifier: Programming Language :: Python :: 3.11
Requires-Dist: deepdiff (>=5.8.0,<6.0.0)
Requires-Dist: fire (>=0.5.0,<0.6.0)
Requires-Dist: ruamel.yaml (>=0.17.21,<0.18.0)
